checkio_task_tester
