Metadata-Version: 1.1
Name: checkio-task-tester
Version: 0.0.4
Summary: CheckiO common line interface for debugging missions on *.checkio.org
Home-page: https://github.com/CheckiO/checkio-task-tester
Author: CheckiO
Author-email: a.lyabah@checkio.org
License: UNKNOWN
Download-URL: https://github.com/CheckiO/checkio-task-tester/tarball/0.0.4
Platform: UNKNOWN
